<!-- SHALL have 1..* author. MAY be device or person. -->
<author>
  <time value="{{.Time}}" />
  <assignedAuthor>
  {{range .Ids}}
    {{template "_id.xml" .}}
  {{end}}
  {{range .Addresses}}
    {{template "_address.xml" .}}
  {{end}}
  {{range .Telecoms}}
    {{template "_telecom.xml" .}}
  {{end}}

  {{if .Person.First}}
    <assignedPerson>
      <name>
        <given>{{.Person.First}}</given>
        <family>{{.Person.Last}}</family>
      </name>
    </assignedPerson>
  {{else if .Device.Model}}
    <assignedAuthoringDevice>
       <manufacturerModelName>{{.Device.Model}}</manufacturerModelName>
       <softwareName>{{.Device.Name}}</softwareName>
     </assignedAuthoringDevice>
  {{end}}

  {{template "_organization.xml" .Organization}}
  </assignedAuthor>
</author>
